timeslib/__init__.py
timeslib/appdata.py
timeslib/misc.py
timeslib/reporting.py
timeslib/sets.py
timeslib-0.5.0.dist-info/licenses/LICENSE
timeslib-0.5.0.dist-info/METADATA
timeslib-0.5.0.dist-info/WHEEL
timeslib-0.5.0.dist-info/top_level.txt
timeslib-0.5.0.dist-info/RECORD
