Metadata-Version: 2.4
Name: timeslib
Version: 0.5.0
Summary: Useful code for working with TIMES
Home-page: https://github.com/olejandro/timeslib
Author: Olexandr Balyk
Author-email: olex@energymodelling.club
Project-URL: Bug Tracker, https://github.com/olejandro/timeslib/issues
Classifier: Programming Language :: Python :: 3
Classifier: License :: OSI Approved :: GNU Affero General Public License v3
Classifier: Operating System :: OS Independent
Requires-Python: >=3.6
License-File: LICENSE
Dynamic: license-file
